a_stock_mcp_server/__init__.py
a_stock_mcp_server/__main__.py
a_stock_mcp_server/base.py
a_stock_mcp_server/cli_tool.py
a_stock_mcp_server/data_sources/__init__.py
a_stock_mcp_server/data_sources/akshare_source.py
a_stock_mcp_server/data_sources/base.py
a_stock_mcp_server/data_sources/source_manager.py
a_stock_mcp_server/local_test.py
a_stock_mcp_server/server.py
a_stock_mcp_server/test_client.py
a_stock_mcp_server/tools/__init__.py
a_stock_mcp_server/tools/base.py
a_stock_mcp_server/tools/financial_data.py
a_stock_mcp_server/tools/market_summary.py
a_stock_mcp_server/tools/realtime_price.py
a_stock_mcp_server/tools/stock_history.py
a_stock_mcp_server/tools/stock_info.py
a_stock_mcp_server-1.1.1.dist-info/METADATA
a_stock_mcp_server-1.1.1.dist-info/WHEEL
a_stock_mcp_server-1.1.1.dist-info/entry_points.txt
a_stock_mcp_server-1.1.1.dist-info/licenses/LICENSE
a_stock_mcp_server-1.1.1.dist-info/RECORD
