Metadata-Version: 2.4
Name: a-stock-mcp-server
Version: 1.1.1
Summary: A股实时行情MCP服务器 - 基于Model Context Protocol的A股数据查询工具
License-File: LICENSE
Keywords: mcp,stock,china,a-share,real-time,financial,data,investment,trading
Author: Llldmiao
Author-email: llldmiao@users.noreply.github.com
Requires-Python: >=3.11,<4.0
Classifier: Development Status :: 5 - Production/Stable
Classifier: Intended Audience :: Developers
Classifier: Intended Audience :: Financial and Insurance Industry
Classifier: License :: OSI Approved :: MIT License
Classifier: Operating System :: OS Independent
Classifier: Programming Language :: Python :: 3
Classifier: Programming Language :: Python :: 3.11
Classifier: Programming Language :: Python :: 3.12
Classifier: Programming Language :: Python :: 3.13
Classifier: Programming Language :: Python :: 3.14
Classifier: Topic :: Internet :: WWW/HTTP :: Dynamic Content
Classifier: Topic :: Office/Business :: Financial :: Investment
Classifier: Topic :: Scientific/Engineering :: Information Analysis
Classifier: Topic :: Software Development :: Libraries :: Python Modules
Requires-Dist: aiohttp (>=3.8.0,<4.0.0)
Requires-Dist: akshare (>=1.12.0,<2.0.0)
Requires-Dist: mcp (>=1.0.0,<2.0.0)
Requires-Dist: numpy (>=1.24.0,<2.0.0)
Requires-Dist: pandas (>=2.0.0,<3.0.0)
Project-URL: Bug Reports, https://github.com/Llldmiao/a-stock-mcp-server/issues
Project-URL: Changelog, https://github.com/Llldmiao/a-stock-mcp-server/blob/main/CHANGELOG.md
Project-URL: Documentation, https://github.com/Llldmiao/a-stock-mcp-server#readme
Project-URL: Homepage, https://github.com/Llldmiao/a-stock-mcp-server
Project-URL: Repository, https://github.com/Llldmiao/a-stock-mcp-server
Project-URL: Source, https://github.com/Llldmiao/a-stock-mcp-server
